polysearch/__init__.py
polysearch/algorithms/__init__.py
polysearch/algorithms/a_star.py
polysearch/algorithms/best_first.py
polysearch/algorithms/branch_and_bound.py
polysearch/algorithms/breadth_first.py
polysearch/algorithms/depth_first.py
polysearch/algorithms/hill_climbing.py
polysearch/algorithms/iterative_deepening.py
polysearch/algorithms/uniform_cost.py
polysearch/data_structures/__init__.py
polysearch/data_structures/priority_queue.py
polysearch/data_structures/queue.py
polysearch/data_structures/stack.py
polysearch/interfaces/__init__.py
polysearch/interfaces/state_space_problem.py
polysearch/problems/__init__.py
polysearch/problems/maze.py
polysearch/problems/missionaries_and_cannibals.py
polysearch/problems/n_queens.py
polysearch-0.0.2.dist-info/LICENSE.txt
polysearch-0.0.2.dist-info/METADATA
polysearch-0.0.2.dist-info/WHEEL
polysearch-0.0.2.dist-info/top_level.txt
polysearch-0.0.2.dist-info/RECORD
