Metadata-Version: 2.1
Name: polysearch
Version: 0.0.2
Summary: A collection of state space search algorithms.
Home-page: https://github.com/chaseburton/polysearch
Author: Chase Burton Taylor
Author-email: ctaylor@citycollege.sheffield.eu
Classifier: Development Status :: 3 - Alpha
Classifier: Intended Audience :: Developers
Classifier: License :: OSI Approved :: MIT License
Classifier: Programming Language :: Python :: 3
Classifier: Programming Language :: Python :: 3.7
Classifier: Programming Language :: Python :: 3.8
Classifier: Programming Language :: Python :: 3.9
License-File: LICENSE.txt
